LICENSE.txt
MANIFEST.in
README.rst
setup.py
statkey/__init__.py
statkey.egg-info/PKG-INFO
statkey.egg-info/SOURCES.txt
statkey.egg-info/dependency_links.txt
statkey.egg-info/entry_points.txt
statkey.egg-info/not-zip-safe
statkey.egg-info/top_level.txt