Metadata-Version: 1.1
Name: statkey
Version: 0.2
Summary: A simple script to make the commands 'git status'/'git diff' or 'hg status'/'hg diff' run with a one key command - the s key.
Home-page: UNKNOWN
Author: Colm O'Connor
Author-email: colm.oconnor.github@gmail.com
License: MIT
Keywords: development environment tool git svn hg mercurial
Platform: UNKNOWN
Classifier: Development Status :: 3 - Alpha
Classifier: Intended Audience :: Developers
Classifier: License :: OSI Approved :: MIT License
Classifier: Topic :: Software Development :: Build Tools
Classifier: Programming Language :: Python :: 2
Classifier: Programming Language :: Python :: 2.6
Classifier: Programming Language :: Python :: 2.7
